<?xml version="1.0" encoding="UTF-8" ?><root><rootID type="dict"><ID type="int">41682</ID><Название type="str">Накопитель SSD 2.5&quot; 240GB INTEL (SSDSC2CW240A310)</Название><Артикул type="str">SSDSC2CW240A310</Артикул><Код_товара type="str">U0034198</Код_товара><Цена type="float">173.84</Цена><Короткое_описание type="str">внутренний, 520, Тип флеш-памяти - MLC, SATA 6Gb/s, 550Mb/s (SATA 6 Gb/s), 520Mb/s (SATA 6 Gb/s), 1.2 млн. часов</Короткое_описание><Описание type="str">Твердотельные диски  SSD INTEL 520 240GB 2.5&quot; (SSDSC2CW240A310) построены на базе 25-нанометровой высококачественной флэш-памяти Intel NAND. Они позволяют повысить производительность ПК в самых важных областях. Благодаря скорости случайного чтения до 50 000 операций ввода/вывода в секунду (IOPS) и скорости последовательного чтения до 550 МБ/с ваш ПК будет быстро выполнять самые разнообразные приложения и обрабатывать ресурсоемкие задачи.</Описание><key name="Гарантия, мес." type="str">36</key><Фото type="str">http://opt.brain.com.ua/static/images/prod_img/9/8/U0034198_big.jpg</Фото><Производитель type="str">INTEL</Производитель><Модель type="str">2.5&quot;  240GB</Модель><Тип type="str">внутренний</Тип><Серия type="str">520</Серия><Объём_памяти type="str">240 GB</Объём_памяти><Тип_флеш-памяти type="str">MLC</Тип_флеш-памяти><Форм-фактор type="str">2.5&quot;</Форм-фактор><Интерфейс type="str">SATA 6Gb/s</Интерфейс><key name="Скорость чтения, макс." type="str">550Mb/s (SATA 6 Gb/s)</key><key name="Скорость записи, макс." type="str">520Mb/s (SATA 6 Gb/s)</key><Наработка_на_отказ type="str">1.2 млн. часов</Наработка_на_отказ><Тип_поставки type="str">OEM</Тип_поставки><Страна_производства type="str">Гонконг</Страна_производства><key name="Гарантия, мес" type="str">36</key></rootID></root>